pkgsym/__init__.py
pkgsym/__main__.py
pkgsym-0.2.4.dist-info/LICENSE.txt
pkgsym-0.2.4.dist-info/METADATA
pkgsym-0.2.4.dist-info/WHEEL
pkgsym-0.2.4.dist-info/entry_points.txt
pkgsym-0.2.4.dist-info/top_level.txt
pkgsym-0.2.4.dist-info/RECORD
